BYOST/__init__.py
BYOST/build.py
BYOST/merge_spec.py
BYOST/template.py
BYOST/visualize.py
BYOST/files/Hsiao_SED_V3_Ia.fits
BYOST-0.0.13.dist-info/METADATA
BYOST-0.0.13.dist-info/WHEEL
BYOST-0.0.13.dist-info/top_level.txt
BYOST-0.0.13.dist-info/RECORD
